CHANGES.txt
LICENSE.txt
MANIFEST.in
README.txt
setup.py
js/__init__.py
js.glyphicons.egg-info/PKG-INFO
js.glyphicons.egg-info/SOURCES.txt
js.glyphicons.egg-info/dependency_links.txt
js.glyphicons.egg-info/entry_points.txt
js.glyphicons.egg-info/namespace_packages.txt
js.glyphicons.egg-info/not-zip-safe
js.glyphicons.egg-info/requires.txt
js.glyphicons.egg-info/top_level.txt
js/glyphicons/__init__.py
js/glyphicons/test_glyphicons.txt
js/glyphicons/resources/glyphicons-white.png
js/glyphicons/resources/glyphicons.css
js/glyphicons/resources/glyphicons.min.css
js/glyphicons/resources/glyphicons.png