Metadata-Version: 1.0
Name: js.glyphicons
Version: 1.7
Summary: Fanstatic packaging of GLYPHICONS
Home-page: UNKNOWN
Author: UNKNOWN
Author-email: UNKNOWN
License: CC BY 3.0
Platform: UNKNOWN
